{
  "basics": {
    "name": "Dennis Ezell",
    "label": "Software Engineer",
    "picture": "https://s.gravatar.com/avatar/995f6c8a3b8e85d9c77a8c1b67b9d870?s=80",
    "email": "Dezell2002@gmail.com",
    "phone": "(318) 331-5154",
    "website": "",
    "summary": "Proactive software developer with experience in full stack development and maintenance of complex and business critical systems. Currently working within a Microsoft technology stack with previous experience in a Java/Oracle stack.",
    "location": {
      "address": "3100 Deborah Dr., Apt 97",
      "postalCode": "71201",
      "city": "Monroe",
      "countryCode": "US",
      "region": "Louisiana"
    },
    "profiles": []
  },
  "work": [
	{
      "company": "CentralSquare Technologies (Merged Aptean public sector with Superion, Tritech, and Zuercher)",
      "position": "Software Engineer",
      "website": "https://www.centralsqr.com/",
      "startDate": "2018-09-03",
      "summary": "Jurisdiction Online - Project rollout lead team member",
      "highlights": [
		"Self-directed, Full stack Microsoft based development using ASP.NET combined with SQL Server",
		"Lead member of project rollout team responsible for bringing new clients into the Jurisdiction Online system",
		"Work with solution architects to provide overall project technical direction",
		"Mentor new and less experienced developers",
		"Serve as the lead project developer"		
	  ]
    },
	{
      "company": "Aptean (Acquired Jurisdiction Online from Praeses)",
      "position": "Software Engineer",
      "website": "https://www.aptean.com/our-company/about-us",
      "startDate": "2017-12-04",
      "endDate": "2018-09-03",
      "summary": "Jurisdiction Online - Project rollout lead team member",
      "highlights": [
		"Self-directed, Full stack Microsoft based development using ASP.NET combined with SQL Server",
		"Lead member of project rollout team responsible for bringing new clients into the Jurisdiction Online system",
		"Design and implement new Case Management module within Jurisdiction Online leveraging new Hangfire service",
		"Adopt Aurelia as the go-forward front-end technology for new development",
		"Work with solution architects to provide overall project technical direction",
		"Mentor new and less experienced developers",
		"Serve as the lead project developer"		
	  ]
    },
	{
      "company": "Praeses",
      "position": "Software Developer III",
      "website": "https://www.praeses.com/",
      "startDate": "2017-06-05",
      "endDate": "2017-12-01",
      "summary": "Jurisdiction Online - Project rollout senior team member",
      "highlights": [
		"Self-directed, Full stack Microsoft based development using ASP.NET combined with SQL Server",
		"Senior member of project rollout team responsible for bringing new clients into the Jurisdiction Online system",
		"Design and implement new Exam Management module within Jurisdiction Online",
		"Serve as backup to lead project developer"		
	  ]
    },
	{
      "company": "Praeses",
      "position": "Software Developer II",
      "website": "https://www.praeses.com/",
      "startDate": "2016-12-19",
      "endDate": "2017-06-02",
      "summary": "Jurisdiction Online - Project rollout team member",
      "highlights": [
		"Self-directed, full stack Microsoft based development using ASP.NET combined with SQL Server",
		"Operate within an Agile Scrum team",
		"Member of project rollout team responsible for bringing new clients into the Jurisdiction Online system",
		"Design and implement new Exam Management module within Jurisdiction Online"
	  ]
	},
	    {
      "company": "CenturyLink",
      "position": "Software Developer II",
      "website": "https://www.centurylink.com/",
      "startDate": "2016-06-06",
      "endDate": "2016-12-16",
      "summary": "Business Support Systems - Project initiative team member",
      "highlights": [
        "UI/Middleware development using Spring based REST services and Spring MVC for front-end interfaces",
		"Cross-functional Agile team member for product initiative to consolidate legacy systems",
		"Create REST based web-services for new project initiative data models",
        "Create UI code to consume new REST web service data"
      ]
    },
	{
      "company": "Praeses",
      "position": "Software Developer I",
      "website": "https://www.praeses.com/",
      "startDate": "2015-08-30",
      "endDate": "2016-06-01",
      "summary": "Jurisdiction Online - Customer support queue team member",
      "highlights": [
		"Full stack Microsoft based development using ASP.NET combined with SQL Server",
		"Operate within an Agile methodology using Kanban for ticket prioritization",
		"Work with support staff and clients to perform defect resolution"
	  ]
	},
	{
      "company": "CenturyLink",
      "position": "Software Developer II",
      "website": "https://www.centurylink.com/",
      "startDate": "2012-06-10",
      "endDate": "2015-08-27",
      "summary": "Ensemble UI - Billing system user interface team member",
      "highlights": [
        "UI development using the Spring MVC framework in conjunction with JavaServer Pages",
		"Collaborate with development teams on the execution of ideas/projects.",
        "Create low-level design documentation based on system requirements ",
        "Implement new code functionality based on approved design",
		"Operate within a Waterfall methodology"	
      ]
    } 
  ],
  "education": [
    {
      "institution": "University of Oklahoma",
      "area": "Information Technology",
      "studyType": "Bachelor",
      "startDate": "2011-06-01",
      "endDate": "2014-01-01",
      "gpa": "4.0",
      "courses": [
        "DB1101 - Basic SQL",
        "CS2011 - Java Introduction"
      ]
    }
  ],
  "publications": [
    {
      "name": "Video compression for 3d media",
      "publisher": "Hooli",
      "releaseDate": "2014-10-01",
      "website": "https://en.wikipedia.org/wiki/Silicon_Valley_(TV_series)",
      "summary": "Innovative middle-out compression algorithm that changes the way we store data."
    }
  ],
  "skills": [
    {
      "name": "Web Development",
      "level": "Master",
      "keywords": [
        "HTML",
        "CSS",
        "Javascript"
      ]
    },
    {
      "name": "Compression",
      "level": "Master",
      "keywords": [
        "Mpeg",
        "MP4",
        "GIF"
      ]
    }
  ],
  "languages": [
    {
      "language": "English",
      "fluency": "Native speaker"
    }
  ],
  "interests": [
    {
      "name": "Wildlife",
      "keywords": [
        "Ferrets",
        "Unicorns"
      ]
    }
  ],
  "references": [
    {
      "name": "Erlich Bachman",
      "reference": "It is my pleasure to recommend Richard, his performance working as a consultant for Main St. Company proved that he will be a valuable addition to any company."
    }
  ]
}